greeter/__init__.py
greeter/helloworld_pb2.py
greeter-0.0.1471128612.dist-info/DESCRIPTION.rst
greeter-0.0.1471128612.dist-info/METADATA
greeter-0.0.1471128612.dist-info/RECORD
greeter-0.0.1471128612.dist-info/WHEEL
greeter-0.0.1471128612.dist-info/metadata.json
greeter-0.0.1471128612.dist-info/top_level.txt
