Metadata-Version: 2.0
Name: greeter
Version: 0.0.1471128612
Summary: A sample Python project
Home-page: https://github.com/stackmachine/greeter
Author: StackMachine
Author-email: contact@stackmachine.com
License: MIT
Keywords: grpc stackmachine
Platform: UNKNOWN
Classifier: Development Status :: 3 - Alpha
Classifier: Intended Audience :: Developers
Classifier: Topic :: Software Development :: Build Tools
Classifier: License :: OSI Approved :: MIT License
Classifier: Programming Language :: Python :: 2
Classifier: Programming Language :: Python :: 2.7
Classifier: Programming Language :: Python :: 3
Classifier: Programming Language :: Python :: 3.5
Requires-Dist: grpcio (==1.0.0rc2)
